tethys_utils/__init__.py
tethys_utils/altitude_io.py
tethys_utils/backwards.py
tethys_utils/data_io.py
tethys_utils/grid.py
tethys_utils/hilltop.py
tethys_utils/misc.py
tethys_utils/processing.py
tethys_utils/raster.py
tethys_utils/s3.py
tethys_utils/time_series.py
tethys_utils/titan.py
tethys_utils/datasets/__init__.py
tethys_utils/tests/__init__.py
tethys_utils/tests/test_email.py
tethys_utils/tests/test_titan.py
tethys_utils/tests/utest_grid.py
tethys_utils/tests/utest_processify.py
tethys_utils/tests/utest_utils.py
tethys_utils/tests/working.py
tethys_utils-0.8.4.dist-info/LICENSE
tethys_utils-0.8.4.dist-info/METADATA
tethys_utils-0.8.4.dist-info/WHEEL
tethys_utils-0.8.4.dist-info/top_level.txt
tethys_utils-0.8.4.dist-info/RECORD
