Metadata-Version: 2.1
Name: tethys-utils
Version: 0.8.4
Summary: tethys utilities
Home-page: https://github.com/tethys-ts/tethys-utils
Author: Mike Kittridge
Author-email: mullenkamp1@gmail.com
License: Apache
Keywords: tethys
Classifier: Development Status :: 3 - Alpha
Classifier: Intended Audience :: Developers
Classifier: Topic :: Software Development :: Build Tools
Classifier: License :: OSI Approved :: Apache Software License
Classifier: Programming Language :: Python :: 2
Classifier: Programming Language :: Python :: 2.7
Classifier: Programming Language :: Python :: 3
Classifier: Programming Language :: Python :: 3.4
Classifier: Programming Language :: Python :: 3.5
Classifier: Programming Language :: Python :: 3.6
License-File: LICENSE
Requires-Dist: tethys-data-models (>=0.4.11)
Requires-Dist: requests
Requires-Dist: tethysts (>=4.5.6)
Requires-Dist: rioxarray
Requires-Dist: numexpr
Requires-Dist: dask
Requires-Dist: numcodecs
Requires-Dist: hydrointerp
Requires-Dist: geojson
Requires-Dist: dill
Requires-Dist: hdf5tools (>=0.1.9)
